[
  {
    "Id": 1,
    "Nome": "Danilo Rodrigues de Oliveia",
    "Email": "danilo.rodrigues38@gmail.com",
    "Ativo": true
  },
  {
    "Id": 2,
    "Nome": "Danilo Rodrigues",
    "Email": "danilo.rodrigues@gmail.com",
    "Ativo": true
  },
  {
    "Id": 3,
    "Nome": "Danilo Oliveira",
    "Email": "danilo.oliveira@gmail.com",
    "Ativo": true
  },
  {
    "Id": 4,
    "Nome": "Fulano de Tal",
    "Email": "fulanodetal@gmail.com",
    "Ativo": true
  },
  {
    "Id": 5,
    "Nome": "Sicrano de Tal",
    "Email": "sicranodetal@gmail.com",
    "Ativo": true
  },
  {
    "Id": 6,
    "Nome": "Fulano Rodrigues",
    "Email": "fulanorodrigues@gmail.com",
    "Ativo": true
  },
  {
    "Id": 7,
    "Nome": "Emanuel Nobrega",
    "Email": "emanuelnobrega@gmail.com",
    "Ativo": true
  },
  {
    "Id": 8,
    "Nome": "Pato Donald",
    "Email": "quackshot@gmail.com",
    "Ativo": true
  },
  {
    "Id": 9,
    "Nome": "Huguinho Patinho",
    "Email": "huguinho.patinho@gmail.com",
    "Ativo": true
  },
  {
    "Id": 10,
    "Nome": "Tio Patinhas",
    "Email": "tio.patinhas@gmail.com",
    "Ativo": true
  },
  {
    "Id": 11,
    "Nome": "Zezinho patinho",
    "Email": "zezinho.patinho@gmail.com",
    "Ativo": true
  },
  {
    "Id": 12,
    "Nome": "Luizinho patinho",
    "Email": "luizinho.patinho@gmail.com",
    "Ativo": true
  },
  {
    "Id": 13,
    "Nome": "Joaquim Silva",
    "Email": "joaquim.silva@gmail.com",
    "Ativo": true
  },
  {
    "Id": 14,
    "Nome": "Maria Souza",
    "Email": "maria.souza@gmail.com",
    "Ativo": true
  },
  {
    "Id": 15,
    "Nome": "Carlos Almeida",
    "Email": "carlos.almeida@gmail.com",
    "Ativo": true
  },
  {
    "Id": 16,
    "Nome": "Ana Paula Santos",
    "Email": "ana.paula.santos@gmail.com",
    "Ativo": true
  },
  {
    "Id": 17,
    "Nome": "Ricardo Pereira",
    "Email": "ricardo.pereira@gmail.com",
    "Ativo": true
  },
  {
    "Id": 18,
    "Nome": "Fernanda Lima",
    "Email": "fernanda.lima@gmail.com",
    "Ativo": true
  },
  {
    "Id": 19,
    "Nome": "Pedro Henrique",
    "Email": "pedro.henrique@gmail.com",
    "Ativo": true
  },
  {
    "Id": 20,
    "Nome": "Juliana Costa",
    "Email": "juliana.costa@gmail.com",
    "Ativo": true
  },
  {
    "Id": 21,
    "Nome": "Marcos Vinícius",
    "Email": "marcos.vinicius@gmail.com",
    "Ativo": true
  },
  {
    "Id": 22,
    "Nome": "Aline Barros",
    "Email": "aline.barros@gmail.com",
    "Ativo": true
  },
  {
    "Id": 23,
    "Nome": "Rafael Nunes",
    "Email": "rafael.nunes@gmail.com",
    "Ativo": true
  },
  {
    "Id": 24,
    "Nome": "Patrícia Ferreira",
    "Email": "patricia.ferreira@gmail.com",
    "Ativo": true
  },
  {
    "Id": 25,
    "Nome": "Gustavo Martins",
    "Email": "gustavo.martins@gmail.com",
    "Ativo": true
  },
  {
    "Id": 26,
    "Nome": "Isabela Mendes",
    "Email": "isabela.mendes@gmail.com",
    "Ativo": true
  },
  {
    "Id": 27,
    "Nome": "Eduardo Moreira",
    "Email": "eduardo.moreira@gmail.com",
    "Ativo": true
  },
  {
    "Id": 28,
    "Nome": "Renata Oliveira",
    "Email": "renata.oliveira@gmail.com",
    "Ativo": true
  },
  {
    "Id": 29,
    "Nome": "André Souza",
    "Email": "andre.souza@gmail.com",
    "Ativo": true
  },
  {
    "Id": 30,
    "Nome": "Bianca Rodrigues",
    "Email": "bianca.rodrigues@gmail.com",
    "Ativo": true
  },
  {
    "Id": 31,
    "Nome": "Fabio Rocha",
    "Email": "fabio.rocha@gmail.com",
    "Ativo": true
  },
  {
    "Id": 32,
    "Nome": "Mariana Azevedo",
    "Email": "mariana.azevedo@gmail.com",
    "Ativo": true
  }
]
